concretefhe_numpy-0.0.10-py3.9-nspkg.pth
concretefhe/numpy/__init__.py
concretefhe/numpy/file.py
concretefhe_numpy-0.0.10.dist-info/LICENSE
concretefhe_numpy-0.0.10.dist-info/METADATA
concretefhe_numpy-0.0.10.dist-info/WHEEL
concretefhe_numpy-0.0.10.dist-info/namespace_packages.txt
concretefhe_numpy-0.0.10.dist-info/top_level.txt
concretefhe_numpy-0.0.10.dist-info/RECORD
